[{"model": "admin.logentry", "pk": 1, "fields": {"action_time": "2021-01-14T18:33:54.865Z", "user": 1, "content_type": 7, "object_id": "1", "object_repr": "My Site", "action_flag": 1, "change_message": "[{\"added\": {}}]"}}, {"model": "admin.logentry", "pk": 2, "fields": {"action_time": "2021-01-14T18:48:44.369Z", "user": 1, "content_type": 7, "object_id": "1", "object_repr": "Main object (1)", "action_flag": 3, "change_message": ""}}, {"model": "admin.logentry", "pk": 3, "fields": {"action_time": "2021-01-14T18:48:54.413Z", "user": 1, "content_type": 7, "object_id": "2", "object_repr": "Main object (2)", "action_flag": 1, "change_message": "[{\"added\": {}}]"}}, {"model": "admin.logentry", "pk": 4, "fields": {"action_time": "2021-01-14T18:49:11.442Z", "user": 1, "content_type": 7, "object_id": "3", "object_repr": "Main object (3)", "action_flag": 1, "change_message": "[{\"added\": {}}]"}}, {"model": "admin.logentry", "pk": 5, "fields": {"action_time": "2021-01-14T18:54:13.767Z", "user": 1, "content_type": 7, "object_id": "2", "object_repr": "Main object (2)", "action_flag": 2, "change_message": "[{\"changed\": {\"fields\": [\"Name\"]}}]"}}, {"model": "admin.logentry", "pk": 6, "fields": {"action_time": "2021-01-14T18:54:28.299Z", "user": 1, "content_type": 7, "object_id": "3", "object_repr": "Main object (3)", "action_flag": 2, "change_message": "[{\"changed\": {\"fields\": [\"Name\"]}}]"}}, {"model": "admin.logentry", "pk": 7, "fields": {"action_time": "2021-01-14T18:57:47.285Z", "user": 1, "content_type": 7, "object_id": "3", "object_repr": "Main object (3)", "action_flag": 2, "change_message": "[{\"changed\": {\"fields\": [\"About\"]}}]"}}, {"model": "admin.logentry", "pk": 8, "fields": {"action_time": "2021-01-14T18:58:43.333Z", "user": 1, "content_type": 7, "object_id": "2", "object_repr": "Main object (2)", "action_flag": 2, "change_message": "[{\"changed\": {\"fields\": [\"About\"]}}]"}}, {"model": "admin.logentry", "pk": 9, "fields": {"action_time": "2021-01-14T19:05:56.214Z", "user": 1, "content_type": 7, "object_id": "2", "object_repr": "Main object (2)", "action_flag": 2, "change_message": "[{\"changed\": {\"fields\": [\"Name\"]}}]"}}, {"model": "admin.logentry", "pk": 10, "fields": {"action_time": "2021-01-14T19:11:09.451Z", "user": 1, "content_type": 7, "object_id": "3", "object_repr": "Main object (3)", "action_flag": 3, "change_message": ""}}, {"model": "admin.logentry", "pk": 11, "fields": {"action_time": "2021-01-14T19:15:26.676Z", "user": 1, "content_type": 7, "object_id": "2", "object_repr": "Main object (2)", "action_flag": 2, "change_message": "[{\"changed\": {\"fields\": [\"Set name\"]}}]"}}, {"model": "admin.logentry", "pk": 12, "fields": {"action_time": "2021-01-16T12:26:12.727Z", "user": 1, "content_type": 8, "object_id": "1", "object_repr": "Test", "action_flag": 1, "change_message": "[{\"added\": {}}]"}}, {"model": "admin.logentry", "pk": 13, "fields": {"action_time": "2021-01-16T12:26:48.223Z", "user": 1, "content_type": 8, "object_id": "2", "object_repr": "Test 2", "action_flag": 1, "change_message": "[{\"added\": {}}]"}}, {"model": "admin.logentry", "pk": 14, "fields": {"action_time": "2021-01-16T12:36:31.516Z", "user": 1, "content_type": 8, "object_id": "3", "object_repr": "Test 3", "action_flag": 1, "change_message": "[{\"added\": {}}]"}}, {"model": "admin.logentry", "pk": 15, "fields": {"action_time": "2021-01-16T12:37:01.326Z", "user": 1, "content_type": 8, "object_id": "3", "object_repr": "Test 3", "action_flag": 3, "change_message": ""}}, {"model": "admin.logentry", "pk": 16, "fields": {"action_time": "2021-01-16T13:05:38.455Z", "user": 1, "content_type": 8, "object_id": "1", "object_repr": "Test", "action_flag": 2, "change_message": "[{\"changed\": {\"fields\": [\"Body txt\"]}}]"}}, {"model": "admin.logentry", "pk": 17, "fields": {"action_time": "2021-01-16T13:05:48.820Z", "user": 1, "content_type": 8, "object_id": "2", "object_repr": "Test 2", "action_flag": 2, "change_message": "[{\"changed\": {\"fields\": [\"Body txt\"]}}]"}}, {"model": "admin.logentry", "pk": 18, "fields": {"action_time": "2021-01-16T16:13:50.595Z", "user": 1, "content_type": 8, "object_id": "2", "object_repr": "Test 2", "action_flag": 2, "change_message": "[{\"changed\": {\"fields\": [\"Author\"]}}]"}}, {"model": "admin.logentry", "pk": 19, "fields": {"action_time": "2021-01-16T16:13:54.403Z", "user": 1, "content_type": 8, "object_id": "2", "object_repr": "Test 2", "action_flag": 2, "change_message": "[]"}}, {"model": "admin.logentry", "pk": 20, "fields": {"action_time": "2021-01-16T16:14:06.428Z", "user": 1, "content_type": 8, "object_id": "1", "object_repr": "Test", "action_flag": 2, "change_message": "[{\"changed\": {\"fields\": [\"Author\"]}}]"}}, {"model": "admin.logentry", "pk": 21, "fields": {"action_time": "2021-01-16T16:14:53.770Z", "user": 1, "content_type": 8, "object_id": "4", "object_repr": "Test 3", "action_flag": 1, "change_message": "[{\"added\": {}}]"}}, {"model": "admin.logentry", "pk": 22, "fields": {"action_time": "2021-01-17T15:21:14.758Z", "user": 1, "content_type": 8, "object_id": "7", "object_repr": "Test Img", "action_flag": 3, "change_message": ""}}, {"model": "admin.logentry", "pk": 23, "fields": {"action_time": "2021-01-17T15:21:14.760Z", "user": 1, "content_type": 8, "object_id": "6", "object_repr": "Hello", "action_flag": 3, "change_message": ""}}, {"model": "admin.logentry", "pk": 24, "fields": {"action_time": "2021-01-17T15:21:14.761Z", "user": 1, "content_type": 8, "object_id": "5", "object_repr": "Post Test", "action_flag": 3, "change_message": ""}}, {"model": "admin.logentry", "pk": 25, "fields": {"action_time": "2021-01-17T15:21:14.763Z", "user": 1, "content_type": 8, "object_id": "4", "object_repr": "Test 3", "action_flag": 3, "change_message": ""}}, {"model": "admin.logentry", "pk": 26, "fields": {"action_time": "2021-01-17T15:21:14.764Z", "user": 1, "content_type": 8, "object_id": "2", "object_repr": "Test 2", "action_flag": 3, "change_message": ""}}, {"model": "admin.logentry", "pk": 27, "fields": {"action_time": "2021-01-17T15:21:14.765Z", "user": 1, "content_type": 8, "object_id": "1", "object_repr": "Test", "action_flag": 3, "change_message": ""}}, {"model": "admin.logentry", "pk": 28, "fields": {"action_time": "2021-01-17T15:34:58.804Z", "user": 1, "content_type": 8, "object_id": "8", "object_repr": "Test Img", "action_flag": 3, "change_message": ""}}, {"model": "admin.logentry", "pk": 29, "fields": {"action_time": "2021-01-18T19:21:05.407Z", "user": 1, "content_type": 9, "object_id": "1", "object_repr": "Cystic Fibrosis", "action_flag": 1, "change_message": "[{\"added\": {}}]"}}, {"model": "admin.logentry", "pk": 30, "fields": {"action_time": "2021-01-18T20:12:06.818Z", "user": 1, "content_type": 9, "object_id": "4", "object_repr": "Another test", "action_flag": 3, "change_message": ""}}, {"model": "admin.logentry", "pk": 31, "fields": {"action_time": "2021-01-18T20:12:06.820Z", "user": 1, "content_type": 9, "object_id": "3", "object_repr": "Yes", "action_flag": 3, "change_message": ""}}, {"model": "admin.logentry", "pk": 32, "fields": {"action_time": "2021-01-18T20:12:06.821Z", "user": 1, "content_type": 9, "object_id": "2", "object_repr": "Test", "action_flag": 3, "change_message": ""}}, {"model": "admin.logentry", "pk": 33, "fields": {"action_time": "2021-01-18T20:12:06.822Z", "user": 1, "content_type": 9, "object_id": "1", "object_repr": "Cystic Fibrosis", "action_flag": 3, "change_message": ""}}, {"model": "admin.logentry", "pk": 34, "fields": {"action_time": "2021-01-21T19:35:01.073Z", "user": 1, "content_type": 8, "object_id": "16", "object_repr": "Hello", "action_flag": 2, "change_message": "[{\"changed\": {\"fields\": [\"Ocatid\"]}}]"}}, {"model": "admin.logentry", "pk": 35, "fields": {"action_time": "2021-01-21T19:53:18.337Z", "user": 1, "content_type": 8, "object_id": "17", "object_repr": "CF Tips", "action_flag": 2, "change_message": "[{\"changed\": {\"fields\": [\"Ocatid\"]}}]"}}, {"model": "admin.logentry", "pk": 36, "fields": {"action_time": "2021-01-21T19:53:24.303Z", "user": 1, "content_type": 8, "object_id": "18", "object_repr": "Hello", "action_flag": 2, "change_message": "[{\"changed\": {\"fields\": [\"Short txt\", \"Body txt\", \"Ocatid\"]}}]"}}, {"model": "admin.logentry", "pk": 37, "fields": {"action_time": "2021-01-21T19:53:37.195Z", "user": 1, "content_type": 8, "object_id": "19", "object_repr": "Testing", "action_flag": 2, "change_message": "[{\"changed\": {\"fields\": [\"Short txt\", \"Body txt\", \"Ocatid\"]}}]"}}, {"model": "admin.logentry", "pk": 38, "fields": {"action_time": "2021-01-27T19:21:37.525Z", "user": 1, "content_type": 11, "object_id": "19", "object_repr": "Conor O Reilly", "action_flag": 3, "change_message": ""}}, {"model": "admin.logentry", "pk": 39, "fields": {"action_time": "2021-01-27T19:21:37.529Z", "user": 1, "content_type": 11, "object_id": "18", "object_repr": "Conor O Reilly", "action_flag": 3, "change_message": ""}}, {"model": "admin.logentry", "pk": 40, "fields": {"action_time": "2021-01-27T19:21:37.530Z", "user": 1, "content_type": 11, "object_id": "17", "object_repr": "Conor O Reilly", "action_flag": 3, "change_message": ""}}, {"model": "admin.logentry", "pk": 41, "fields": {"action_time": "2021-01-27T19:21:37.532Z", "user": 1, "content_type": 11, "object_id": "16", "object_repr": "Conor O Reilly", "action_flag": 3, "change_message": ""}}, {"model": "admin.logentry", "pk": 42, "fields": {"action_time": "2021-01-27T19:21:37.533Z", "user": 1, "content_type": 11, "object_id": "15", "object_repr": "Conor O Reilly", "action_flag": 3, "change_message": ""}}, {"model": "admin.logentry", "pk": 43, "fields": {"action_time": "2021-01-27T19:21:37.534Z", "user": 1, "content_type": 11, "object_id": "14", "object_repr": "Conor O Reilly", "action_flag": 3, "change_message": ""}}, {"model": "admin.logentry", "pk": 44, "fields": {"action_time": "2021-01-27T19:21:37.536Z", "user": 1, "content_type": 11, "object_id": "13", "object_repr": "Conor O Reilly", "action_flag": 3, "change_message": ""}}, {"model": "admin.logentry", "pk": 45, "fields": {"action_time": "2021-01-27T19:21:37.537Z", "user": 1, "content_type": 11, "object_id": "12", "object_repr": "Conor O Reilly", "action_flag": 3, "change_message": ""}}, {"model": "admin.logentry", "pk": 46, "fields": {"action_time": "2021-01-27T19:21:37.538Z", "user": 1, "content_type": 11, "object_id": "11", "object_repr": "Conor O Reilly", "action_flag": 3, "change_message": ""}}, {"model": "admin.logentry", "pk": 47, "fields": {"action_time": "2021-01-27T19:21:37.539Z", "user": 1, "content_type": 11, "object_id": "10", "object_repr": "Conor O Reilly", "action_flag": 3, "change_message": ""}}, {"model": "admin.logentry", "pk": 48, "fields": {"action_time": "2021-01-27T19:21:37.541Z", "user": 1, "content_type": 11, "object_id": "9", "object_repr": "Conor O Reilly", "action_flag": 3, "change_message": ""}}, {"model": "admin.logentry", "pk": 49, "fields": {"action_time": "2021-01-27T19:21:37.542Z", "user": 1, "content_type": 11, "object_id": "8", "object_repr": "Conor O Reilly", "action_flag": 3, "change_message": ""}}, {"model": "admin.logentry", "pk": 50, "fields": {"action_time": "2021-01-27T19:21:37.543Z", "user": 1, "content_type": 11, "object_id": "7", "object_repr": "Conor O Reilly", "action_flag": 3, "change_message": ""}}, {"model": "admin.logentry", "pk": 51, "fields": {"action_time": "2021-01-27T19:21:37.544Z", "user": 1, "content_type": 11, "object_id": "6", "object_repr": "Conor O Reilly", "action_flag": 3, "change_message": ""}}, {"model": "admin.logentry", "pk": 52, "fields": {"action_time": "2021-01-27T19:21:37.545Z", "user": 1, "content_type": 11, "object_id": "5", "object_repr": "Conor O Reilly", "action_flag": 3, "change_message": ""}}, {"model": "admin.logentry", "pk": 53, "fields": {"action_time": "2021-01-27T19:21:37.546Z", "user": 1, "content_type": 11, "object_id": "4", "object_repr": "Conor O Reilly", "action_flag": 3, "change_message": ""}}, {"model": "admin.logentry", "pk": 54, "fields": {"action_time": "2021-01-27T19:21:37.547Z", "user": 1, "content_type": 11, "object_id": "3", "object_repr": "Conor O Reilly", "action_flag": 3, "change_message": ""}}, {"model": "admin.logentry", "pk": 55, "fields": {"action_time": "2021-01-27T19:21:37.548Z", "user": 1, "content_type": 11, "object_id": "2", "object_repr": "Conor O Reilly", "action_flag": 3, "change_message": ""}}, {"model": "admin.logentry", "pk": 56, "fields": {"action_time": "2021-01-27T19:21:37.550Z", "user": 1, "content_type": 11, "object_id": "1", "object_repr": "Conor O Reilly", "action_flag": 3, "change_message": ""}}, {"model": "admin.logentry", "pk": 57, "fields": {"action_time": "2021-02-01T21:17:39.711Z", "user": 1, "content_type": 4, "object_id": "2", "object_repr": "admin2", "action_flag": 3, "change_message": ""}}, {"model": "admin.logentry", "pk": 58, "fields": {"action_time": "2021-02-03T20:49:00.829Z", "user": 1, "content_type": 3, "object_id": "1", "object_repr": "Test", "action_flag": 1, "change_message": "[{\"added\": {}}]"}}, {"model": "admin.logentry", "pk": 59, "fields": {"action_time": "2021-02-03T21:25:49.303Z", "user": 1, "content_type": 4, "object_id": "4", "object_repr": "demo", "action_flag": 2, "change_message": "[{\"changed\": {\"fields\": [\"Groups\"]}}]"}}, {"model": "admin.logentry", "pk": 60, "fields": {"action_time": "2021-02-06T15:51:19.007Z", "user": 1, "content_type": 2, "object_id": "1", "object_repr": "admin | log entry | Can add log entry", "action_flag": 3, "change_message": ""}}, {"model": "admin.logentry", "pk": 61, "fields": {"action_time": "2021-02-06T15:51:19.008Z", "user": 1, "content_type": 2, "object_id": "2", "object_repr": "admin | log entry | Can change log entry", "action_flag": 3, "change_message": ""}}, {"model": "admin.logentry", "pk": 62, "fields": {"action_time": "2021-02-06T15:51:19.010Z", "user": 1, "content_type": 2, "object_id": "3", "object_repr": "admin | log entry | Can delete log entry", "action_flag": 3, "change_message": ""}}, {"model": "admin.logentry", "pk": 63, "fields": {"action_time": "2021-02-06T15:51:19.011Z", "user": 1, "content_type": 2, "object_id": "4", "object_repr": "admin | log entry | Can view log entry", "action_flag": 3, "change_message": ""}}, {"model": "admin.logentry", "pk": 64, "fields": {"action_time": "2021-02-06T15:51:19.013Z", "user": 1, "content_type": 2, "object_id": "9", "object_repr": "auth | group | Can add group", "action_flag": 3, "change_message": ""}}, {"model": "admin.logentry", "pk": 65, "fields": {"action_time": "2021-02-06T15:51:19.014Z", "user": 1, "content_type": 2, "object_id": "10", "object_repr": "auth | group | Can change group", "action_flag": 3, "change_message": ""}}, {"model": "admin.logentry", "pk": 66, "fields": {"action_time": "2021-02-06T15:51:19.015Z", "user": 1, "content_type": 2, "object_id": "11", "object_repr": "auth | group | Can delete group", "action_flag": 3, "change_message": ""}}, {"model": "admin.logentry", "pk": 67, "fields": {"action_time": "2021-02-06T15:51:19.016Z", "user": 1, "content_type": 2, "object_id": "12", "object_repr": "auth | group | Can view group", "action_flag": 3, "change_message": ""}}, {"model": "admin.logentry", "pk": 68, "fields": {"action_time": "2021-02-06T15:51:19.017Z", "user": 1, "content_type": 2, "object_id": "5", "object_repr": "auth | permission | Can add permission", "action_flag": 3, "change_message": ""}}, {"model": "admin.logentry", "pk": 69, "fields": {"action_time": "2021-02-06T15:51:19.018Z", "user": 1, "content_type": 2, "object_id": "6", "object_repr": "auth | permission | Can change permission", "action_flag": 3, "change_message": ""}}, {"model": "admin.logentry", "pk": 70, "fields": {"action_time": "2021-02-06T15:51:19.019Z", "user": 1, "content_type": 2, "object_id": "7", "object_repr": "auth | permission | Can delete permission", "action_flag": 3, "change_message": ""}}, {"model": "admin.logentry", "pk": 71, "fields": {"action_time": "2021-02-06T15:51:19.020Z", "user": 1, "content_type": 2, "object_id": "8", "object_repr": "auth | permission | Can view permission", "action_flag": 3, "change_message": ""}}, {"model": "admin.logentry", "pk": 72, "fields": {"action_time": "2021-02-06T15:51:19.022Z", "user": 1, "content_type": 2, "object_id": "13", "object_repr": "auth | user | Can add user", "action_flag": 3, "change_message": ""}}, {"model": "admin.logentry", "pk": 73, "fields": {"action_time": "2021-02-06T15:51:19.023Z", "user": 1, "content_type": 2, "object_id": "14", "object_repr": "auth | user | Can change user", "action_flag": 3, "change_message": ""}}, {"model": "admin.logentry", "pk": 74, "fields": {"action_time": "2021-02-06T15:51:19.024Z", "user": 1, "content_type": 2, "object_id": "15", "object_repr": "auth | user | Can delete user", "action_flag": 3, "change_message": ""}}, {"model": "admin.logentry", "pk": 75, "fields": {"action_time": "2021-02-06T15:51:19.025Z", "user": 1, "content_type": 2, "object_id": "16", "object_repr": "auth | user | Can view user", "action_flag": 3, "change_message": ""}}, {"model": "admin.logentry", "pk": 76, "fields": {"action_time": "2021-02-06T15:51:19.026Z", "user": 1, "content_type": 2, "object_id": "33", "object_repr": "category | category | Can add category", "action_flag": 3, "change_message": ""}}, {"model": "admin.logentry", "pk": 77, "fields": {"action_time": "2021-02-06T15:51:19.027Z", "user": 1, "content_type": 2, "object_id": "34", "object_repr": "category | category | Can change category", "action_flag": 3, "change_message": ""}}, {"model": "admin.logentry", "pk": 78, "fields": {"action_time": "2021-02-06T15:51:19.028Z", "user": 1, "content_type": 2, "object_id": "35", "object_repr": "category | category | Can delete category", "action_flag": 3, "change_message": ""}}, {"model": "admin.logentry", "pk": 79, "fields": {"action_time": "2021-02-06T15:51:19.029Z", "user": 1, "content_type": 2, "object_id": "36", "object_repr": "category | category | Can view category", "action_flag": 3, "change_message": ""}}, {"model": "admin.logentry", "pk": 80, "fields": {"action_time": "2021-02-06T15:51:19.030Z", "user": 1, "content_type": 2, "object_id": "41", "object_repr": "contactform | contact form | Can add contact form", "action_flag": 3, "change_message": ""}}, {"model": "admin.logentry", "pk": 81, "fields": {"action_time": "2021-02-06T15:51:19.031Z", "user": 1, "content_type": 2, "object_id": "42", "object_repr": "contactform | contact form | Can change contact form", "action_flag": 3, "change_message": ""}}, {"model": "admin.logentry", "pk": 82, "fields": {"action_time": "2021-02-06T15:51:19.032Z", "user": 1, "content_type": 2, "object_id": "43", "object_repr": "contactform | contact form | Can delete contact form", "action_flag": 3, "change_message": ""}}, {"model": "admin.logentry", "pk": 83, "fields": {"action_time": "2021-02-06T15:51:19.033Z", "user": 1, "content_type": 2, "object_id": "44", "object_repr": "contactform | contact form | Can view contact form", "action_flag": 3, "change_message": ""}}, {"model": "admin.logentry", "pk": 84, "fields": {"action_time": "2021-02-06T15:51:19.034Z", "user": 1, "content_type": 2, "object_id": "17", "object_repr": "contenttypes | content type | Can add content type", "action_flag": 3, "change_message": ""}}, {"model": "admin.logentry", "pk": 85, "fields": {"action_time": "2021-02-06T15:51:19.034Z", "user": 1, "content_type": 2, "object_id": "18", "object_repr": "contenttypes | content type | Can change content type", "action_flag": 3, "change_message": ""}}, {"model": "admin.logentry", "pk": 86, "fields": {"action_time": "2021-02-06T15:51:19.035Z", "user": 1, "content_type": 2, "object_id": "19", "object_repr": "contenttypes | content type | Can delete content type", "action_flag": 3, "change_message": ""}}, {"model": "admin.logentry", "pk": 87, "fields": {"action_time": "2021-02-06T15:51:19.036Z", "user": 1, "content_type": 2, "object_id": "20", "object_repr": "contenttypes | content type | Can view content type", "action_flag": 3, "change_message": ""}}, {"model": "admin.logentry", "pk": 88, "fields": {"action_time": "2021-02-06T15:51:19.037Z", "user": 1, "content_type": 2, "object_id": "25", "object_repr": "main | main | Can add main", "action_flag": 3, "change_message": ""}}, {"model": "admin.logentry", "pk": 89, "fields": {"action_time": "2021-02-06T15:51:19.038Z", "user": 1, "content_type": 2, "object_id": "26", "object_repr": "main | main | Can change main", "action_flag": 3, "change_message": ""}}, {"model": "admin.logentry", "pk": 90, "fields": {"action_time": "2021-02-06T15:51:19.039Z", "user": 1, "content_type": 2, "object_id": "27", "object_repr": "main | main | Can delete main", "action_flag": 3, "change_message": ""}}, {"model": "admin.logentry", "pk": 91, "fields": {"action_time": "2021-02-06T15:51:19.040Z", "user": 1, "content_type": 2, "object_id": "28", "object_repr": "main | main | Can view main", "action_flag": 3, "change_message": ""}}, {"model": "admin.logentry", "pk": 92, "fields": {"action_time": "2021-02-06T15:51:19.042Z", "user": 1, "content_type": 2, "object_id": "45", "object_repr": "manager | manager | Can add manager", "action_flag": 3, "change_message": ""}}, {"model": "admin.logentry", "pk": 93, "fields": {"action_time": "2021-02-06T15:51:19.043Z", "user": 1, "content_type": 2, "object_id": "46", "object_repr": "manager | manager | Can change manager", "action_flag": 3, "change_message": ""}}, {"model": "admin.logentry", "pk": 94, "fields": {"action_time": "2021-02-06T15:51:19.044Z", "user": 1, "content_type": 2, "object_id": "47", "object_repr": "manager | manager | Can delete manager", "action_flag": 3, "change_message": ""}}, {"model": "admin.logentry", "pk": 95, "fields": {"action_time": "2021-02-06T15:51:19.045Z", "user": 1, "content_type": 2, "object_id": "48", "object_repr": "manager | manager | Can view manager", "action_flag": 3, "change_message": ""}}, {"model": "admin.logentry", "pk": 96, "fields": {"action_time": "2021-02-06T15:51:19.046Z", "user": 1, "content_type": 2, "object_id": "29", "object_repr": "posts | posts | Can add posts", "action_flag": 3, "change_message": ""}}, {"model": "admin.logentry", "pk": 97, "fields": {"action_time": "2021-02-06T15:51:19.047Z", "user": 1, "content_type": 2, "object_id": "30", "object_repr": "posts | posts | Can change posts", "action_flag": 3, "change_message": ""}}, {"model": "admin.logentry", "pk": 98, "fields": {"action_time": "2021-02-06T15:51:19.048Z", "user": 1, "content_type": 2, "object_id": "31", "object_repr": "posts | posts | Can delete posts", "action_flag": 3, "change_message": ""}}, {"model": "admin.logentry", "pk": 99, "fields": {"action_time": "2021-02-06T15:51:19.049Z", "user": 1, "content_type": 2, "object_id": "32", "object_repr": "posts | posts | Can view posts", "action_flag": 3, "change_message": ""}}, {"model": "admin.logentry", "pk": 100, "fields": {"action_time": "2021-02-06T15:51:19.050Z", "user": 1, "content_type": 2, "object_id": "21", "object_repr": "sessions | session | Can add session", "action_flag": 3, "change_message": ""}}, {"model": "admin.logentry", "pk": 101, "fields": {"action_time": "2021-02-06T15:51:19.051Z", "user": 1, "content_type": 2, "object_id": "22", "object_repr": "sessions | session | Can change session", "action_flag": 3, "change_message": ""}}, {"model": "admin.logentry", "pk": 102, "fields": {"action_time": "2021-02-06T15:51:19.052Z", "user": 1, "content_type": 2, "object_id": "23", "object_repr": "sessions | session | Can delete session", "action_flag": 3, "change_message": ""}}, {"model": "admin.logentry", "pk": 103, "fields": {"action_time": "2021-02-06T15:51:19.053Z", "user": 1, "content_type": 2, "object_id": "24", "object_repr": "sessions | session | Can view session", "action_flag": 3, "change_message": ""}}, {"model": "admin.logentry", "pk": 104, "fields": {"action_time": "2021-02-06T15:51:19.054Z", "user": 1, "content_type": 2, "object_id": "37", "object_repr": "subcategory | sub category | Can add sub category", "action_flag": 3, "change_message": ""}}, {"model": "admin.logentry", "pk": 105, "fields": {"action_time": "2021-02-06T15:51:19.055Z", "user": 1, "content_type": 2, "object_id": "38", "object_repr": "subcategory | sub category | Can change sub category", "action_flag": 3, "change_message": ""}}, {"model": "admin.logentry", "pk": 106, "fields": {"action_time": "2021-02-06T15:51:19.056Z", "user": 1, "content_type": 2, "object_id": "39", "object_repr": "subcategory | sub category | Can delete sub category", "action_flag": 3, "change_message": ""}}, {"model": "admin.logentry", "pk": 107, "fields": {"action_time": "2021-02-06T15:51:19.057Z", "user": 1, "content_type": 2, "object_id": "40", "object_repr": "subcategory | sub category | Can view sub category", "action_flag": 3, "change_message": ""}}, {"model": "admin.logentry", "pk": 108, "fields": {"action_time": "2021-02-06T16:22:14.882Z", "user": 1, "content_type": 3, "object_id": "4", "object_repr": "masteruser", "action_flag": 1, "change_message": "[{\"added\": {}}]"}}, {"model": "admin.logentry", "pk": 109, "fields": {"action_time": "2021-02-06T16:22:36.378Z", "user": 1, "content_type": 4, "object_id": "1", "object_repr": "conororeilly", "action_flag": 2, "change_message": "[{\"changed\": {\"fields\": [\"Groups\"]}}]"}}, {"model": "admin.logentry", "pk": 110, "fields": {"action_time": "2021-02-06T16:34:10.124Z", "user": 1, "content_type": 4, "object_id": "1", "object_repr": "conororeilly", "action_flag": 2, "change_message": "[{\"changed\": {\"fields\": [\"Groups\"]}}]"}}, {"model": "admin.logentry", "pk": 111, "fields": {"action_time": "2021-02-06T16:35:19.258Z", "user": 1, "content_type": 4, "object_id": "1", "object_repr": "conororeilly", "action_flag": 2, "change_message": "[{\"changed\": {\"fields\": [\"Groups\"]}}]"}}, {"model": "admin.logentry", "pk": 112, "fields": {"action_time": "2021-02-06T16:38:58.602Z", "user": 1, "content_type": 4, "object_id": "1", "object_repr": "conororeilly", "action_flag": 2, "change_message": "[{\"changed\": {\"fields\": [\"Groups\"]}}]"}}, {"model": "admin.logentry", "pk": 113, "fields": {"action_time": "2021-02-06T16:45:28.957Z", "user": 1, "content_type": 4, "object_id": "1", "object_repr": "conororeilly", "action_flag": 2, "change_message": "[{\"changed\": {\"fields\": [\"Groups\"]}}]"}}, {"model": "admin.logentry", "pk": 114, "fields": {"action_time": "2021-04-05T12:07:20.448Z", "user": 1, "content_type": 4, "object_id": "1", "object_repr": "conororeilly", "action_flag": 2, "change_message": "[{\"changed\": {\"fields\": [\"User permissions\"]}}]"}}, {"model": "admin.logentry", "pk": 115, "fields": {"action_time": "2021-04-05T12:09:27.189Z", "user": 1, "content_type": 4, "object_id": "4", "object_repr": "demo", "action_flag": 2, "change_message": "[{\"changed\": {\"fields\": [\"User permissions\"]}}]"}}, {"model": "admin.logentry", "pk": 116, "fields": {"action_time": "2021-04-05T12:43:40.363Z", "user": 1, "content_type": 3, "object_id": "5", "object_repr": "test", "action_flag": 2, "change_message": "[{\"changed\": {\"fields\": [\"Permissions\"]}}]"}}, {"model": "admin.logentry", "pk": 117, "fields": {"action_time": "2021-04-05T14:30:19.253Z", "user": 1, "content_type": 2, "object_id": "102", "object_repr": "main | main | master_user", "action_flag": 1, "change_message": "[{\"added\": {}}]"}}, {"model": "admin.logentry", "pk": 118, "fields": {"action_time": "2021-04-05T14:34:02.175Z", "user": 1, "content_type": 4, "object_id": "1", "object_repr": "conororeilly", "action_flag": 2, "change_message": "[{\"changed\": {\"fields\": [\"User permissions\"]}}]"}}, {"model": "admin.logentry", "pk": 119, "fields": {"action_time": "2021-04-05T14:36:10.887Z", "user": 1, "content_type": 4, "object_id": "1", "object_repr": "conororeilly", "action_flag": 2, "change_message": "[{\"changed\": {\"fields\": [\"User permissions\"]}}]"}}, {"model": "admin.logentry", "pk": 120, "fields": {"action_time": "2021-04-05T14:49:39.502Z", "user": 1, "content_type": 4, "object_id": "4", "object_repr": "demo", "action_flag": 2, "change_message": "[{\"changed\": {\"fields\": [\"Groups\"]}}]"}}, {"model": "admin.logentry", "pk": 121, "fields": {"action_time": "2021-04-05T14:51:46.442Z", "user": 1, "content_type": 4, "object_id": "4", "object_repr": "demo", "action_flag": 2, "change_message": "[{\"changed\": {\"fields\": [\"Groups\"]}}]"}}, {"model": "admin.logentry", "pk": 122, "fields": {"action_time": "2021-04-05T18:07:22.744Z", "user": 1, "content_type": 13, "object_id": "1", "object_repr": "0851535928", "action_flag": 3, "change_message": ""}}, {"model": "admin.logentry", "pk": 123, "fields": {"action_time": "2021-04-05T18:21:10.545Z", "user": 1, "content_type": 13, "object_id": "2", "object_repr": "0851535988", "action_flag": 3, "change_message": ""}}, {"model": "admin.logentry", "pk": 124, "fields": {"action_time": "2021-04-06T11:15:21.977Z", "user": 1, "content_type": 4, "object_id": "1", "object_repr": "conororeilly", "action_flag": 2, "change_message": "[{\"changed\": {\"fields\": [\"First name\", \"Last name\"]}}]"}}, {"model": "admin.logentry", "pk": 125, "fields": {"action_time": "2021-04-06T12:16:32.545Z", "user": 1, "content_type": 4, "object_id": "4", "object_repr": "demo", "action_flag": 2, "change_message": "[{\"changed\": {\"fields\": [\"Groups\"]}}]"}}, {"model": "admin.logentry", "pk": 126, "fields": {"action_time": "2021-04-06T12:16:41.281Z", "user": 1, "content_type": 4, "object_id": "4", "object_repr": "demo", "action_flag": 2, "change_message": "[{\"changed\": {\"fields\": [\"Groups\"]}}]"}}, {"model": "admin.logentry", "pk": 127, "fields": {"action_time": "2021-04-12T20:50:51.212Z", "user": 1, "content_type": 8, "object_id": "39", "object_repr": "Another Test", "action_flag": 3, "change_message": ""}}, {"model": "admin.logentry", "pk": 128, "fields": {"action_time": "2021-04-12T20:50:51.214Z", "user": 1, "content_type": 8, "object_id": "38", "object_repr": "Hello", "action_flag": 3, "change_message": ""}}, {"model": "admin.logentry", "pk": 129, "fields": {"action_time": "2021-04-12T20:50:51.215Z", "user": 1, "content_type": 8, "object_id": "37", "object_repr": "What is Up?", "action_flag": 3, "change_message": ""}}, {"model": "admin.logentry", "pk": 130, "fields": {"action_time": "2021-04-12T20:50:51.217Z", "user": 1, "content_type": 8, "object_id": "36", "object_repr": "Who is On?", "action_flag": 3, "change_message": ""}}, {"model": "admin.logentry", "pk": 131, "fields": {"action_time": "2021-04-12T20:50:51.218Z", "user": 1, "content_type": 8, "object_id": "35", "object_repr": "Yes", "action_flag": 3, "change_message": ""}}, {"model": "admin.logentry", "pk": 132, "fields": {"action_time": "2021-04-12T20:50:51.220Z", "user": 1, "content_type": 8, "object_id": "34", "object_repr": "Hello All the World", "action_flag": 3, "change_message": ""}}, {"model": "admin.logentry", "pk": 133, "fields": {"action_time": "2021-04-12T20:50:51.221Z", "user": 1, "content_type": 8, "object_id": "33", "object_repr": "Progeria OK", "action_flag": 3, "change_message": ""}}, {"model": "auth.permission", "pk": 102, "fields": {"name": "master_user", "content_type": 7, "codename": "master_user"}}, {"model": "auth.permission", "pk": 103, "fields": {"name": "Can add log entry", "content_type": 1, "codename": "add_logentry"}}, {"model": "auth.permission", "pk": 104, "fields": {"name": "Can change log entry", "content_type": 1, "codename": "change_logentry"}}, {"model": "auth.permission", "pk": 105, "fields": {"name": "Can delete log entry", "content_type": 1, "codename": "delete_logentry"}}, {"model": "auth.permission", "pk": 106, "fields": {"name": "Can view log entry", "content_type": 1, "codename": "view_logentry"}}, {"model": "auth.permission", "pk": 107, "fields": {"name": "Can add permission", "content_type": 2, "codename": "add_permission"}}, {"model": "auth.permission", "pk": 108, "fields": {"name": "Can change permission", "content_type": 2, "codename": "change_permission"}}, {"model": "auth.permission", "pk": 109, "fields": {"name": "Can delete permission", "content_type": 2, "codename": "delete_permission"}}, {"model": "auth.permission", "pk": 110, "fields": {"name": "Can view permission", "content_type": 2, "codename": "view_permission"}}, {"model": "auth.permission", "pk": 111, "fields": {"name": "Can add group", "content_type": 3, "codename": "add_group"}}, {"model": "auth.permission", "pk": 112, "fields": {"name": "Can change group", "content_type": 3, "codename": "change_group"}}, {"model": "auth.permission", "pk": 113, "fields": {"name": "Can delete group", "content_type": 3, "codename": "delete_group"}}, {"model": "auth.permission", "pk": 114, "fields": {"name": "Can view group", "content_type": 3, "codename": "view_group"}}, {"model": "auth.permission", "pk": 115, "fields": {"name": "Can add user", "content_type": 4, "codename": "add_user"}}, {"model": "auth.permission", "pk": 116, "fields": {"name": "Can change user", "content_type": 4, "codename": "change_user"}}, {"model": "auth.permission", "pk": 117, "fields": {"name": "Can delete user", "content_type": 4, "codename": "delete_user"}}, {"model": "auth.permission", "pk": 118, "fields": {"name": "Can view user", "content_type": 4, "codename": "view_user"}}, {"model": "auth.permission", "pk": 119, "fields": {"name": "Can add content type", "content_type": 5, "codename": "add_contenttype"}}, {"model": "auth.permission", "pk": 120, "fields": {"name": "Can change content type", "content_type": 5, "codename": "change_contenttype"}}, {"model": "auth.permission", "pk": 121, "fields": {"name": "Can delete content type", "content_type": 5, "codename": "delete_contenttype"}}, {"model": "auth.permission", "pk": 122, "fields": {"name": "Can view content type", "content_type": 5, "codename": "view_contenttype"}}, {"model": "auth.permission", "pk": 123, "fields": {"name": "Can add session", "content_type": 6, "codename": "add_session"}}, {"model": "auth.permission", "pk": 124, "fields": {"name": "Can change session", "content_type": 6, "codename": "change_session"}}, {"model": "auth.permission", "pk": 125, "fields": {"name": "Can delete session", "content_type": 6, "codename": "delete_session"}}, {"model": "auth.permission", "pk": 126, "fields": {"name": "Can view session", "content_type": 6, "codename": "view_session"}}, {"model": "auth.permission", "pk": 127, "fields": {"name": "Can add main", "content_type": 7, "codename": "add_main"}}, {"model": "auth.permission", "pk": 128, "fields": {"name": "Can change main", "content_type": 7, "codename": "change_main"}}, {"model": "auth.permission", "pk": 129, "fields": {"name": "Can delete main", "content_type": 7, "codename": "delete_main"}}, {"model": "auth.permission", "pk": 130, "fields": {"name": "Can view main", "content_type": 7, "codename": "view_main"}}, {"model": "auth.permission", "pk": 131, "fields": {"name": "Can add posts", "content_type": 8, "codename": "add_posts"}}, {"model": "auth.permission", "pk": 132, "fields": {"name": "Can change posts", "content_type": 8, "codename": "change_posts"}}, {"model": "auth.permission", "pk": 133, "fields": {"name": "Can delete posts", "content_type": 8, "codename": "delete_posts"}}, {"model": "auth.permission", "pk": 134, "fields": {"name": "Can view posts", "content_type": 8, "codename": "view_posts"}}, {"model": "auth.permission", "pk": 135, "fields": {"name": "Can add category", "content_type": 9, "codename": "add_category"}}, {"model": "auth.permission", "pk": 136, "fields": {"name": "Can change category", "content_type": 9, "codename": "change_category"}}, {"model": "auth.permission", "pk": 137, "fields": {"name": "Can delete category", "content_type": 9, "codename": "delete_category"}}, {"model": "auth.permission", "pk": 138, "fields": {"name": "Can view category", "content_type": 9, "codename": "view_category"}}, {"model": "auth.permission", "pk": 139, "fields": {"name": "Can add sub category", "content_type": 10, "codename": "add_subcategory"}}, {"model": "auth.permission", "pk": 140, "fields": {"name": "Can change sub category", "content_type": 10, "codename": "change_subcategory"}}, {"model": "auth.permission", "pk": 141, "fields": {"name": "Can delete sub category", "content_type": 10, "codename": "delete_subcategory"}}, {"model": "auth.permission", "pk": 142, "fields": {"name": "Can view sub category", "content_type": 10, "codename": "view_subcategory"}}, {"model": "auth.permission", "pk": 143, "fields": {"name": "Can add contact form", "content_type": 11, "codename": "add_contactform"}}, {"model": "auth.permission", "pk": 144, "fields": {"name": "Can change contact form", "content_type": 11, "codename": "change_contactform"}}, {"model": "auth.permission", "pk": 145, "fields": {"name": "Can delete contact form", "content_type": 11, "codename": "delete_contactform"}}, {"model": "auth.permission", "pk": 146, "fields": {"name": "Can view contact form", "content_type": 11, "codename": "view_contactform"}}, {"model": "auth.permission", "pk": 147, "fields": {"name": "Can add manager", "content_type": 12, "codename": "add_manager"}}, {"model": "auth.permission", "pk": 148, "fields": {"name": "Can change manager", "content_type": 12, "codename": "change_manager"}}, {"model": "auth.permission", "pk": 149, "fields": {"name": "Can delete manager", "content_type": 12, "codename": "delete_manager"}}, {"model": "auth.permission", "pk": 150, "fields": {"name": "Can view manager", "content_type": 12, "codename": "view_manager"}}, {"model": "auth.permission", "pk": 151, "fields": {"name": "Can add newsletter", "content_type": 13, "codename": "add_newsletter"}}, {"model": "auth.permission", "pk": 152, "fields": {"name": "Can change newsletter", "content_type": 13, "codename": "change_newsletter"}}, {"model": "auth.permission", "pk": 153, "fields": {"name": "Can delete newsletter", "content_type": 13, "codename": "delete_newsletter"}}, {"model": "auth.permission", "pk": 154, "fields": {"name": "Can view newsletter", "content_type": 13, "codename": "view_newsletter"}}, {"model": "auth.permission", "pk": 155, "fields": {"name": "Can add comment", "content_type": 14, "codename": "add_comment"}}, {"model": "auth.permission", "pk": 156, "fields": {"name": "Can change comment", "content_type": 14, "codename": "change_comment"}}, {"model": "auth.permission", "pk": 157, "fields": {"name": "Can delete comment", "content_type": 14, "codename": "delete_comment"}}, {"model": "auth.permission", "pk": 158, "fields": {"name": "Can view comment", "content_type": 14, "codename": "view_comment"}}, {"model": "auth.group", "pk": 4, "fields": {"name": "masteruser", "permissions": []}}, {"model": "auth.group", "pk": 5, "fields": {"name": "test", "permissions": []}}, {"model": "auth.user", "pk": 1, "fields": {"password": "pbkdf2_sha256$216000$St23wrs9dDt5$wphS9loKWC1qOhlmbQjJWgpm39QxhGixD6/qxnYNXwk=", "last_login": "2021-04-12T20:50:35.910Z", "is_superuser": true, "username": "conororeilly", "first_name": "Conor", "last_name": "O Reilly", "email": "x17101701@student.ncirl.ie", "is_staff": true, "is_active": true, "date_joined": "2020-12-19T16:15:12Z", "groups": [4], "user_permissions": []}}, {"model": "auth.user", "pk": 4, "fields": {"password": "pbkdf2_sha256$216000$vH2dbITJWjnJ$dcGj6UkrZ/gD4pdhev+Us3SmJ1U4eNhFUUWjSrnDQ2E=", "last_login": "2021-04-06T15:26:48.349Z", "is_superuser": false, "username": "demo", "first_name": "", "last_name": "", "email": "demo1@gmail.com", "is_staff": false, "is_active": true, "date_joined": "2021-02-03T21:14:06Z", "groups": [5], "user_permissions": []}}, {"model": "auth.user", "pk": 5, "fields": {"password": "pbkdf2_sha256$216000$bqoyicqS7mhu$W0hGtAYvN2EQUUX4WXD/3yiN7Geoz4lKCnqKErEVZgU=", "last_login": "2021-04-05T14:47:15.979Z", "is_superuser": false, "username": "ryanhade", "first_name": "", "last_name": "", "email": "hade@gmail.com", "is_staff": false, "is_active": true, "date_joined": "2021-04-05T14:46:54.962Z", "groups": [], "user_permissions": []}}, {"model": "contenttypes.contenttype", "pk": 1, "fields": {"app_label": "admin", "model": "logentry"}}, {"model": "contenttypes.contenttype", "pk": 2, "fields": {"app_label": "auth", "model": "permission"}}, {"model": "contenttypes.contenttype", "pk": 3, "fields": {"app_label": "auth", "model": "group"}}, {"model": "contenttypes.contenttype", "pk": 4, "fields": {"app_label": "auth", "model": "user"}}, {"model": "contenttypes.contenttype", "pk": 5, "fields": {"app_label": "contenttypes", "model": "contenttype"}}, {"model": "contenttypes.contenttype", "pk": 6, "fields": {"app_label": "sessions", "model": "session"}}, {"model": "contenttypes.contenttype", "pk": 7, "fields": {"app_label": "main", "model": "main"}}, {"model": "contenttypes.contenttype", "pk": 8, "fields": {"app_label": "posts", "model": "posts"}}, {"model": "contenttypes.contenttype", "pk": 9, "fields": {"app_label": "category", "model": "category"}}, {"model": "contenttypes.contenttype", "pk": 10, "fields": {"app_label": "subcategory", "model": "subcategory"}}, {"model": "contenttypes.contenttype", "pk": 11, "fields": {"app_label": "contactform", "model": "contactform"}}, {"model": "contenttypes.contenttype", "pk": 12, "fields": {"app_label": "manager", "model": "manager"}}, {"model": "contenttypes.contenttype", "pk": 13, "fields": {"app_label": "newsletter", "model": "newsletter"}}, {"model": "contenttypes.contenttype", "pk": 14, "fields": {"app_label": "comment", "model": "comment"}}, {"model": "sessions.session", "pk": "58lsaxn0zey956jf8yo0i5h2m82sjkcn", "fields": {"session_data": ".eJxVjEEOwiAQRe_C2hA6MIW6dO8ZyAxDpWpoUtqV8e7apAvd_vfef6lI21ri1vISJ1Fn1anT78aUHrnuQO5Ub7NOc12XifWu6IM2fZ0lPy-H-3dQqJVvjcGN4FgsmDEE63uDAJkBYeDUUSZhCDh4xORcn4MDsd4mIoPBWnbq_QHDozcM:1lW3Vz:gMvQQvW9p9LtVljzLyH706RNr_i1yLUo0gGmjMtcYVY", "expire_date": "2021-04-26T20:50:35.913Z"}}, {"model": "sessions.session", "pk": "jztz86l7jl01sbs9sn2m558lc9m159ud", "fields": {"session_data": ".eJxVjEEOwiAQRe_C2hA6MIW6dO8ZyAxDpWpoUtqV8e7apAvd_vfef6lI21ri1vISJ1Fn1anT78aUHrnuQO5Ub7NOc12XifWu6IM2fZ0lPy-H-3dQqJVvjcGN4FgsmDEE63uDAJkBYeDUUSZhCDh4xORcn4MDsd4mIoPBWnbq_QHDozcM:1l8QDL:wOaWM1QIqQgGZflY_A0gM4IHslDafnqYyqs8C3S9b7U", "expire_date": "2021-02-20T16:13:39.980Z"}}, {"model": "sessions.session", "pk": "urzxxiv1apy29ym5brsf6bq4o0hh91m0", "fields": {"session_data": ".eJxVjDsOwyAQRO9CHSECmE_K9DkDWtglOIlAMnYV-e62JRdJM8W8N_NlAZa5hKXTFEZkN3Zll98uQnpTPQC-oD4bT63O0xj5ofCTdv5oSJ_76f4dFOhlXwuJPko0IknptMZELjqFkgSRQk9Wm0FlJazdUxsPRNnlIXkFHiIiWzfk-Thz:1kqetl:8KcbehvaNbalceKFBAByFyw6-_RsGwZB5l7R_yioXGs", "expire_date": "2021-01-02T16:16:01.993Z"}}, {"model": "sessions.session", "pk": "vnw6zxwoatzw3cgxbfes87gydch4kehs", "fields": {"session_data": ".eJxVjEEOwiAQRe_C2hA6MIW6dO8ZyAxDpWpoUtqV8e7apAvd_vfef6lI21ri1vISJ1Fn1anT78aUHrnuQO5Ub7NOc12XifWu6IM2fZ0lPy-H-3dQqJVvjcGN4FgsmDEE63uDAJkBYeDUUSZhCDh4xORcn4MDsd4mIoPBWnbq_QHDozcM:1lVaBy:d5BmR8DXh1B06JhJJcyLhzdnyVV9lKsltXFx5VkIyQk", "expire_date": "2021-04-25T13:31:58.793Z"}}, {"model": "sessions.session", "pk": "y19cr4e0uy38vozlnr3w50ybpodw7x6g", "fields": {"session_data": ".eJxVjEEOwiAQRe_C2hA6MIW6dO8ZyAxDpWpoUtqV8e7apAvd_vfef6lI21ri1vISJ1Fn1anT78aUHrnuQO5Ub7NOc12XifWu6IM2fZ0lPy-H-3dQqJVvjcGN4FgsmDEE63uDAJkBYeDUUSZhCDh4xORcn4MDsd4mIoPBWnbq_QHDozcM:1lW3Kv:98LNTbBQ55WN0_MZArfGOSFjOhyp1AAoVK56NiTeQ3M", "expire_date": "2021-04-26T20:39:09.168Z"}}, {"model": "main.main", "pk": 2, "fields": {"name": "Rare Disease Platform", "about": "<p>Rare Disease Platform provides patients and healthcare professionals a medium to share and discuss rare diseases. Users can create, update and delete blog posts.</p>\r\n", "abouttext": "<p>Curabitur volutpat bibendum molestie. Vestibulum ornare gravida semper. Aliquam a dui suscipit, fringilla metus id, maximus leo. Vivamus sapien arcu, mollis eu pharetra vitae, condimentum in orci. Integer eu sodales dolor. Maecenas elementum arcu eu convallis rhoncus. Donec tortor sapien, euismod a faucibus eget, porttitor quis libero.</p>\r\n\r\n<p>Lorem ipsum dolor sit amet, consectetur adipiscing elit. Nunc sit amet est vel orci luctus sollicitudin. Duis eleifend vestibulum justo, varius semper lacus condimentum dictum. Donec pulvinar a magna ut malesuada. In posuere felis diam, vel sodales metus accumsan in. Duis viverra dui eu pharetra pellentesque. Donec a eros leo. Quisque sed ligula vitae lorem efficitur faucibus. Praesent sit amet imperdiet ante. Nulla id tellus auctor, dictum libero a, malesuada nisi. Nulla in porta nibh, id vestibulum ipsum. Praesent dapibus tempus erat quis aliquet. Donec ac purus id sapien condimentum feugiat.</p>\r\n\r\n<p>Praesent vel mi bibendum, finibus leo ac, condimentum arcu. Pellentesque sem ex, tristique sit amet suscipit in, mattis imperdiet enim. Integer tempus justo nec velit fringilla, eget eleifend neque blandit. Sed tempor magna sed congue auctor. Mauris eu turpis eget tortor ultricies elementum. Phasellus vel placerat orci, a venenatis justo. Phasellus faucibus venenatis nisl vitae vestibulum. Praesent id nibh arcu. Vivamus sagittis accumsan felis, quis vulputate</p>\r\n", "set_name": "Site Settings", "logourl": "/media/distributor-logo-opensuse-icon.png", "logoname": "distributor-logo-opensuse-icon.png", "logourl2": "/media/distributor-logo-opensuse-icon_xlonckL.png", "logoname2": "distributor-logo-opensuse-icon_xlonckL.png"}}, {"model": "category.category", "pk": 5, "fields": {"name": "Cystic Fibrosis", "count": 3}}, {"model": "category.category", "pk": 6, "fields": {"name": "Hansen's Disease", "count": 3}}, {"model": "category.category", "pk": 7, "fields": {"name": "Progeria", "count": 1}}, {"model": "subcategory.subcategory", "pk": 1, "fields": {"name": "Tips", "catname": "Cystic Fibrosis", "catid": 5}}, {"model": "subcategory.subcategory", "pk": 2, "fields": {"name": "Symptoms", "catname": "Hansen's Disease", "catid": 6}}, {"model": "subcategory.subcategory", "pk": 3, "fields": {"name": "Causes", "catname": "Cystic Fibrosis", "catid": 5}}, {"model": "subcategory.subcategory", "pk": 4, "fields": {"name": "Treatments", "catname": "Progeria", "catid": 7}}, {"model": "contactform.contactform", "pk": 1, "fields": {"name": "Conor O Reilly", "email": "oreilly9393@gmail.com", "text": "Yes", "date": "2021/01/27", "time": "19:50"}}, {"model": "contactform.contactform", "pk": 2, "fields": {"name": "Ryan Hade", "email": "hade96@gmail.com", "text": "Testing", "date": "2021/02/01", "time": "19:59"}}, {"model": "manager.manager", "pk": 2, "fields": {"name": "userdemo", "utxt": "demo", "email": "demo1@gmail.com"}}, {"model": "manager.manager", "pk": 3, "fields": {"name": "Ryan Hade", "utxt": "ryanhade", "email": "hade@gmail.com"}}, {"model": "comment.comment", "pk": 1, "fields": {"name": "userdemo", "email": "demo1@gmail.com", "cm": "TESTING", "posts_id": 35, "date": "2021/04/06", "time": "15:3", "status": 1}}, {"model": "comment.comment", "pk": 2, "fields": {"name": "userdemo", "email": "demo1@gmail.com", "cm": "Great content", "posts_id": 35, "date": "2021/04/06", "time": "15:27", "status": 1}}, {"model": "comment.comment", "pk": 3, "fields": {"name": "Ben", "email": "Parker", "cm": "I love your content", "posts_id": 38, "date": "2021/04/06", "time": "15:28", "status": 1}}]